opsAgent/__init__.py
opsAgent/bin/__init__.py
opsAgent/bin/cli.py
opsAgent/config/__init__.py
opsAgent/config/settings.py
opsAgent/lib/__init__.py
opsAgent/lib/auth.py
opsAgent/lib/curl.py
opsAgent/lib/http.py
opsAgent/lib/logger.py
opsAgent/lib/path.py
opsAgent/lib/scheduler.py
opsAgent/lib/status.py
opsAgent/lib/task.py
opsAgent/lib/vars.py
opsAgent-0.0.5.dist-info/LICENSE
opsAgent-0.0.5.dist-info/METADATA
opsAgent-0.0.5.dist-info/WHEEL
opsAgent-0.0.5.dist-info/entry_points.txt
opsAgent-0.0.5.dist-info/top_level.txt
opsAgent-0.0.5.dist-info/RECORD
