Metadata-Version: 2.1
Name: opsAgent
Version: 0.0.5
Summary: Monitoring client based on OpsMgr
Home-page: https://github.com/fanghongbo/opsAgent
Author: fanghongbo
Author-email: 718787573@qq.com
License: MIT
Platform: UNKNOWN
Classifier: Intended Audience :: Developers
Classifier: License :: OSI Approved :: MIT License
Classifier: Natural Language :: English
Classifier: Programming Language :: Python :: 3.5
Classifier: Programming Language :: Python :: 3.6
Classifier: Programming Language :: Python :: Implementation :: CPython
Requires-Python: >=3.5
Requires-Dist: APScheduler (==3.6.1)
Requires-Dist: pycurl (==7.43.0.3)
Requires-Dist: requests (==2.22.0)
Requires-Dist: urllib3 (==1.25.6)
